tgt_grease
