Metadata-Version: 1.1
Name: tgt-grease
Version: 2.3.10
Summary: Modern distributed automation engine built with love by Target
Home-page: UNKNOWN
Author: James E. Bell Jr.
Author-email: james.e.bell@target.com
License: MIT
Keywords: python automated recovery
Platform: UNKNOWN
Classifier: Development Status :: 5 - Production/Stable
Classifier: Programming Language :: Python :: 2
Classifier: Programming Language :: Python :: 3
Classifier: Intended Audience :: System Administrators
Classifier: Intended Audience :: Information Technology
Classifier: Topic :: System
Classifier: License :: OSI Approved :: MIT License
Classifier: Operating System :: MacOS :: MacOS X
Classifier: Operating System :: Microsoft :: Windows :: Windows 7
Classifier: Operating System :: Microsoft :: Windows :: Windows 8
Classifier: Operating System :: Microsoft :: Windows :: Windows 8.1
Classifier: Operating System :: Microsoft :: Windows :: Windows 10
Classifier: Operating System :: POSIX
